pygments_ashen.py
pygments_ashen-0.1.3.dist-info/METADATA
pygments_ashen-0.1.3.dist-info/WHEEL
pygments_ashen-0.1.3.dist-info/entry_points.txt
pygments_ashen-0.1.3.dist-info/licenses/LICENSE
pygments_ashen-0.1.3.dist-info/RECORD
