Metadata-Version: 2.4
Name: pygments-ashen
Version: 0.1.3
Summary: Pygments style for Ashen
Project-URL: Repository, https://git.sr.ht/~ficd/ashen
Author-email: Daniel Fichtinger <daniel@ficd.ca>
License-File: LICENSE
Requires-Python: >=3.12
Requires-Dist: pygments>=2.19.2
